globus_automate_client.py
globus_automate_client-0.19.0.dist-info/LICENSE
globus_automate_client-0.19.0.dist-info/METADATA
globus_automate_client-0.19.0.dist-info/WHEEL
globus_automate_client-0.19.0.dist-info/entry_points.txt
globus_automate_client-0.19.0.dist-info/RECORD
