Metadata-Version: 2.3
Name: globus-automate-client
Version: 0.19.0
Summary: This software is end-of-life.
License: Apache-2.0
Author: Globus
Author-email: support@globus.org
Requires-Python: >=3.9
Classifier: Development Status :: 7 - Inactive
Classifier: License :: OSI Approved :: Apache Software License
Classifier: Programming Language :: Python :: 3
Classifier: Programming Language :: Python :: 3.9
Classifier: Programming Language :: Python :: 3.10
Classifier: Programming Language :: Python :: 3.11
Classifier: Programming Language :: Python :: 3.12
Classifier: Programming Language :: Python :: 3.13
